RobinRollandModel/__init__.py
RobinRollandModel/datautils.py
RobinRollandModel/main.py
RobinRollandModel/pyiron.log
RobinRollandModel/pyironjob.py
aptrajectories-0.1.1.dist-info/LICENSE
aptrajectories-0.1.1.dist-info/METADATA
aptrajectories-0.1.1.dist-info/WHEEL
aptrajectories-0.1.1.dist-info/RECORD
