Metadata-Version: 2.1
Name: aptrajectories
Version: 0.1.1
Summary: Simulates APT trajectories based on Robin Rolland charge equilibration model
License: "Apache 2.0"
Author: skatnagallu
Author-email: s.katnagallu@mpie.de
Requires-Python: >=3.11,<3.12
Classifier: License :: Other/Proprietary License
Classifier: Programming Language :: Python :: 3
Classifier: Programming Language :: Python :: 3.11
Requires-Dist: h5io (>=0.2.2,<0.3.0)
Requires-Dist: nbformat (>=5.9.2,<6.0.0)
Requires-Dist: nglview (>=3.1.1,<4.0.0)
Requires-Dist: numpy (>=1.26.4,<2.0.0)
Requires-Dist: plotly (>=5.20.0,<6.0.0)
Requires-Dist: pyiron (>=0.5.2,<0.6.0)
Requires-Dist: pyiron_base (>=0.7.9,<0.8.0)
Requires-Dist: scipy (>=1.12.0,<2.0.0)
Requires-Dist: tqdm (>=4.66.2,<5.0.0)
